CHANGES.txt
LICENSE.txt
README.txt
setup.py
src/getpaid/__init__.py
src/getpaid.warehouse.egg-info/PKG-INFO
src/getpaid.warehouse.egg-info/SOURCES.txt
src/getpaid.warehouse.egg-info/dependency_links.txt
src/getpaid.warehouse.egg-info/namespace_packages.txt
src/getpaid.warehouse.egg-info/not-zip-safe
src/getpaid.warehouse.egg-info/requires.txt
src/getpaid.warehouse.egg-info/top_level.txt
src/getpaid/warehouse/__init__.py
src/getpaid/warehouse/configure.zcml
src/getpaid/warehouse/i18n.py
src/getpaid/warehouse/interfaces.py
src/getpaid/warehouse/inventory.py
src/getpaid/warehouse/plugin.py
src/getpaid/warehouse/profiles.zcml
src/getpaid/warehouse/router.py
src/getpaid/warehouse/shipment.py
src/getpaid/warehouse/todo.txt
src/getpaid/warehouse/warehouse.py
src/getpaid/warehouse/browser/__init__.py
src/getpaid/warehouse/browser/configure.zcml
src/getpaid/warehouse/browser/content.py
src/getpaid/warehouse/browser/fulfillment-order.pt
src/getpaid/warehouse/browser/fulfillment-warehouse.pt
src/getpaid/warehouse/browser/fulfillment.py
src/getpaid/warehouse/browser/item-collection.pt
src/getpaid/warehouse/browser/order-warehouse.pt
src/getpaid/warehouse/browser/order.py
src/getpaid/warehouse/browser/picklist.pt
src/getpaid/warehouse/browser/warehouse-actions.pt
src/getpaid/warehouse/browser/warehouse-container.pt
src/getpaid/warehouse/browser/warehouse.py
src/getpaid/warehouse/profiles/default/actions.xml
src/getpaid/warehouse/tests/__init__.py
src/getpaid/warehouse/tests/base.py
src/getpaid/warehouse/tests/test_functional.py
src/getpaid/warehouse/tests/test_functional_warehouse_manage.txt
src/getpaid/warehouse/tests/test_functional_warehouse_stock.txt